humancursor/__init__.py
humancursor/system_cursor.py
humancursor/web_cursor.py
humancursor/HCScripter/__init__.py
humancursor/HCScripter/gui.py
humancursor/HCScripter/launch.py
humancursor/test/system.py
humancursor/test/web.py
humancursor/utilities/calculate_and_randomize.py
humancursor/utilities/human_curve_generator.py
humancursor/utilities/web_adjuster.py
udeycursor-1.1.5.dist-info/licenses/LICENSE
udeycursor-1.1.5.dist-info/METADATA
udeycursor-1.1.5.dist-info/WHEEL
udeycursor-1.1.5.dist-info/top_level.txt
udeycursor-1.1.5.dist-info/RECORD
