Metadata-Version: 2.4
Name: UdeyCursor
Version: 1.1.5
Summary: Simulate Human Cursor Movement for Automated Scripts
Author-email: Udey Kumar <drozd.dev@outlook.com>
Project-URL: Homepage, https://github.com/softdev629/UdeyCursor
Classifier: Programming Language :: Python :: 3
Classifier: License :: OSI Approved :: MIT License
Classifier: Operating System :: OS Independent
Requires-Python: >=3.7
License-File: LICENSE
Requires-Dist: selenium>=4.9.0
Requires-Dist: pyautogui>=0.9.53
Requires-Dist: numpy>=1.24.3
Dynamic: license-file
